src/__init__.py
src/api.py
wowotuo-0.6.1.dist-info/LICENSE
wowotuo-0.6.1.dist-info/METADATA
wowotuo-0.6.1.dist-info/WHEEL
wowotuo-0.6.1.dist-info/top_level.txt
wowotuo-0.6.1.dist-info/RECORD
