Metadata-Version: 2.1
Name: wowotuo
Version: 0.6.1
Summary: UNKNOWN
Home-page: https://github.com/songroom2016/dbpystream.git
Author: songroom
Author-email: rustroom@163.com
License: UNKNOWN
Platform: UNKNOWN
Requires-Python: >=3.6
License-File: LICENSE
Requires-Dist: pandas (>=0.28.0)
